ube3_apa/E3dict.csv
ube3_apa/__init__.py
ube3_apa/e3enrich.py
ube3_apa/gui.py
ube3_apa/gui_for_maxqt.py
ube3_apa/maxqt2ube3.py
ube3_apa/unigenedict.csv
ube3_apa-1.3.1.dist-info/LICENSE
ube3_apa-1.3.1.dist-info/METADATA
ube3_apa-1.3.1.dist-info/WHEEL
ube3_apa-1.3.1.dist-info/top_level.txt
ube3_apa-1.3.1.dist-info/RECORD
